{
  "streams": [
    {
      "title": "fdfdfdfdfd",
      "description": "ffffffffff",
      "id": 1
    },
    {
      "title": "Kickin It",
      "description": "You know what I mean",
      "id": 2
    },
    {
      "title": "Kickin It",
      "description": "You know what I mean",
      "id": 3
    },
    {
      "title": "Kickin It",
      "description": "You know what I mean",
      "id": 4
    },
    {
      "title": "Kickin It",
      "description": "You know what I mean",
      "id": 5
    },
    {
      "title": "Kickin It",
      "description": "You know what I mean",
      "id": 6
    },
    {
      "title": "Kickin It",
      "description": "You know what I mean",
      "id": 7
    },
    {
      "title": "Kickin It",
      "description": "You know what I mean",
      "id": 8
    },
    {
      "title": "Kickin It",
      "description": "You know what I mean",
      "id": 9
    },
    {
      "title": "Kickin It",
      "description": "You know what I mean",
      "id": 10
    }
  ]
}